uhu/__init__.py
uhu/config.py
uhu/ui.py
uhu/utils.py
uhu/cli/__init__.py
uhu/cli/_object.py
uhu/cli/config.py
uhu/cli/hardware.py
uhu/cli/package.py
uhu/cli/product.py
uhu/cli/utils.py
uhu/core/__init__.py
uhu/core/_object.py
uhu/core/_options.py
uhu/core/compression.py
uhu/core/hardware.py
uhu/core/install_condition.py
uhu/core/modes.py
uhu/core/object.py
uhu/core/objects.py
uhu/core/options.py
uhu/core/package.py
uhu/core/utils.py
uhu/core/validators.py
uhu/repl/__init__.py
uhu/repl/completers.py
uhu/repl/exceptions.py
uhu/repl/functions.py
uhu/repl/helpers.py
uhu/repl/repl.py
uhu/repl/validators.py
uhu/updatehub/__init__.py
uhu/updatehub/_request.py
uhu/updatehub/api.py
uhu/updatehub/auth.py
uhu/updatehub/http.py
uhu-1.2.0.dist-info/LICENSE
uhu-1.2.0.dist-info/METADATA
uhu-1.2.0.dist-info/WHEEL
uhu-1.2.0.dist-info/entry_points.txt
uhu-1.2.0.dist-info/top_level.txt
uhu-1.2.0.dist-info/RECORD
