Metadata-Version: 2.1
Name: uhu
Version: 1.2.0
Summary: "UpdateHub's firmware update package management utilities"
Home-page: http://www.ossystems.com.br
Author: O.S. Systems Software LTDA
License: GPL-2.0
Keywords: industrial-linux,embedded-linux,embedded,firmware-updates,linux,update-service
Platform: UNKNOWN
Requires-Python: >=3.4
Requires-Dist: click (>=6.5)
Requires-Dist: humanize (>=0.5.1)
Requires-Dist: libarchive-c (>=2.9)
Requires-Dist: progress (>=1.1)
Requires-Dist: prompt-toolkit (<4.0.0,>=2.0.0)
Requires-Dist: pycryptodomex
Requires-Dist: requests (>=2.20.0)
Requires-Dist: rfc3987 (>=1.3)
Requires-Dist: updatehub-package-schema (>=1.1.0)
